pydiverse/pipetest/__init__.py
pydiverse.pipetest-0.0.1.dist-info/LICENSE
pydiverse.pipetest-0.0.1.dist-info/METADATA
pydiverse.pipetest-0.0.1.dist-info/WHEEL
pydiverse.pipetest-0.0.1.dist-info/top_level.txt
pydiverse.pipetest-0.0.1.dist-info/RECORD
