Metadata-Version: 2.1
Name: pydiverse.pipetest
Version: 0.0.1
Summary: An adaption layer for pydiverse.pipedag that simplyfies execution of pipedag steps as unit tests with cache invalidation awareness.
Home-page: https://github.com/pydiverse/pydiverse.pipetest
Author: QuantCo, Inc.
Author-email: noreply@quantco.com
Classifier: Programming Language :: Python :: 3
Classifier: Programming Language :: Python :: 3.8
Classifier: Programming Language :: Python :: 3.9
Classifier: Programming Language :: Python :: 3.10
Requires-Python: >=3.8
License-File: LICENSE
